langextract_bedrock/__init__.py
langextract_bedrock/provider.py
langextract_bedrock-0.1.4.dist-info/licenses/LICENSE
langextract_bedrock-0.1.4.dist-info/METADATA
langextract_bedrock-0.1.4.dist-info/WHEEL
langextract_bedrock-0.1.4.dist-info/entry_points.txt
langextract_bedrock-0.1.4.dist-info/top_level.txt
langextract_bedrock-0.1.4.dist-info/RECORD
