Metadata-Version: 2.4
Name: langextract-bedrock
Version: 0.1.4
Summary: LangExtract provider plugin for AWS Bedrock
Author-email: Andy Hadjigeorgiou <andyxhadji@gmail.com>
License: Apache-2.0
Requires-Python: >=3.10
License-File: LICENSE
Requires-Dist: boto3>=1.40.9
Requires-Dist: langextract>=1.1.1
Dynamic: license-file
